pyflexweb/__init__.py
pyflexweb/cli.py
pyflexweb/client.py
pyflexweb/database.py
pyflexweb/handlers.py
pyflexweb-0.2.3.dist-info/licenses/LICENSE
pyflexweb-0.2.3.dist-info/METADATA
pyflexweb-0.2.3.dist-info/WHEEL
pyflexweb-0.2.3.dist-info/entry_points.txt
pyflexweb-0.2.3.dist-info/top_level.txt
pyflexweb-0.2.3.dist-info/RECORD
