Metadata-Version: 2.4
Name: pyflexweb
Version: 0.2.3
Summary: Download IBKR Flex reports using the Interactive Brokers flex web service
Author-email: Vishal Doshi <vishal.doshi@gmail.com>
License: GPL-3.0-or-later
Classifier: Programming Language :: Python :: 3
Classifier: Programming Language :: Python :: 3.12
Classifier: Programming Language :: Python :: 3.13
Classifier: Programming Language :: Python :: 3.14
Classifier: Operating System :: OS Independent
Requires-Python: >=3.12
License-File: LICENSE
Requires-Dist: requests>=2.25.0
Requires-Dist: platformdirs>=2.0.0
Requires-Dist: click>=8.1.8
Provides-Extra: dev
Requires-Dist: pytest>=6.0.0; extra == "dev"
Requires-Dist: ruff>=0.0.240; extra == "dev"
Requires-Dist: isort>=5.0.0; extra == "dev"
Requires-Dist: toml>=0.10.0; extra == "dev"
Requires-Dist: pre-commit>=3.0.0; extra == "dev"
Dynamic: license-file
